LICENSE
MANIFEST.in
README.md
pyproject.toml
requirements.txt
setup.py
deli/__init__.py
deli/__version__.py
deli/interface.py
deli/serializer.py
deli.egg-info/PKG-INFO
deli.egg-info/SOURCES.txt
deli.egg-info/dependency_links.txt
deli.egg-info/requires.txt
deli.egg-info/top_level.txt
deli/serializers/__init__.py
deli/serializers/choice.py
deli/serializers/csv.py
deli/serializers/dicom.py
deli/serializers/helpers.py
deli/serializers/images.py
deli/serializers/nifty.py
deli/serializers/numpy_.py
deli/serializers/packaged.py
tests/test_serializers.py