Metadata-Version: 2.1
Name: deli
Version: 0.2.4
Summary: Smart serialization and deserialization for (almost) any python object
Home-page: https://github.com/maxme1/deli
Download-URL: https://github.com/maxme1/deli/archive/v0.2.4.tar.gz
Author-email: Max <maxs987@gmail.com>
License: MIT License
Project-URL: Homepage, https://github.com/maxme1/deli
Project-URL: Issues, https://github.com/maxme1/deli/issues
Project-URL: Source, https://github.com/maxme1/deli
Keywords: serialization
Classifier: Development Status :: 3 - Alpha
Classifier: License :: OSI Approved :: MIT License
Classifier: Programming Language :: Python :: 3
Classifier: Programming Language :: Python :: 3.6
Classifier: Programming Language :: Python :: 3.7
Classifier: Programming Language :: Python :: 3.8
Classifier: Programming Language :: Python :: 3.9
Classifier: Programming Language :: Python :: 3.10
Classifier: Programming Language :: Python :: 3.11
Classifier: Programming Language :: Python :: 3 :: Only
Classifier: Operating System :: OS Independent
Requires-Python: >=3.6
License-File: LICENSE
Provides-Extra: all
Requires-Dist: pandas; extra == "all"
Requires-Dist: pydicom; extra == "all"
Requires-Dist: nibabel; extra == "all"
Requires-Dist: numpy; extra == "all"
Requires-Dist: imageio>=2.0.0; extra == "all"
